influx/__init__.py
influx/admin.py
influx/base.py
influx/client.py
influx/config.py
py_influxdb-2020.9.20.dist-info/METADATA
py_influxdb-2020.9.20.dist-info/WHEEL
py_influxdb-2020.9.20.dist-info/top_level.txt
py_influxdb-2020.9.20.dist-info/RECORD
