Metadata-Version: 2.1
Name: py-influxdb
Version: 2020.9.20
Summary: Python Client for Influx DB
Home-page: UNKNOWN
Author: Nikhil K Madhusudhan (nikhilkmdev)
Author-email: nikhilkmdev@gmail.com
Maintainer: Nikhil K Madhusudhan (nikhilkmdev)
Maintainer-email: nikhilkmdev@gmail.com
License: MIT
Keywords: influxdb,influx-db,influx,timeseries,python3
Platform: UNKNOWN
Classifier: License :: OSI Approved :: MIT License
Classifier: Programming Language :: Python :: 3
Classifier: Programming Language :: Python :: 3.7
Requires-Dist: requests (==2.24.0)
Requires-Dist: py-influxdb
